mlsync/__init__.py
mlsync/command_line.py
mlsync/params.py
mlsync/sync.py
mlsync/transfer.py
mlsync/api/__init__.py
mlsync/api/mlflow/__init__.py
mlsync/api/mlflow/mlflow_api.py
mlsync/api/mlflow/mlflow_sync.py
mlsync/api/notion/__init__.py
mlsync/api/notion/client.py
mlsync/api/notion/experiments.py
mlsync/api/notion/notion.py
mlsync/api/notion/notion_api.py
mlsync/api/notion/notion_formatter.py
mlsync/api/notion/notion_sync.py
mlsync/api/notion/page_picker.py
mlsync/consumers/__init__.py
mlsync/consumers/notion/__init__.py
mlsync/consumers/notion/notion_api.py
mlsync/consumers/notion/notion_formatter.py
mlsync/consumers/notion/notion_sync.py
mlsync/consumers/notion/page_picker.py
mlsync/engine/__init__.py
mlsync/engine/diff.py
mlsync/engine/sync.py
mlsync/producers/__init__.py
mlsync/producers/mlflow/__init__.py
mlsync/producers/mlflow/mlflow_api.py
mlsync/producers/mlflow/mlflow_formatter.py
mlsync/producers/mlflow/mlflow_sync.py
mlsync/utils/__init__.py
mlsync/utils/utils.py
mlsync-0.1.4.dist-info/LICENSE
mlsync-0.1.4.dist-info/METADATA
mlsync-0.1.4.dist-info/WHEEL
mlsync-0.1.4.dist-info/entry_points.txt
mlsync-0.1.4.dist-info/top_level.txt
mlsync-0.1.4.dist-info/RECORD
